.gitignore
.travis.yml
MANIFEST.in
README.rst
buildout.cfg
setup.py
githook/__init__.py
githook.egg-info/PKG-INFO
githook.egg-info/SOURCES.txt
githook.egg-info/dependency_links.txt
githook.egg-info/entry_points.txt
githook.egg-info/not-zip-safe
githook.egg-info/requires.txt
githook.egg-info/top_level.txt