Metadata-Version: 1.1
Name: githook
Version: 0.2
Summary: Simple web application that runs a script in response of GitHub post hook.
Home-page: https://github.com/brodul/githook
Author: Andraz Brodnik
Author-email: brodul@brodul.org
License: MIT
Platform: UNKNOWN
Classifier: Development Status :: 4 - Beta
Classifier: Intended Audience :: Developers
Classifier: Intended Audience :: System Administrators
Classifier: License :: OSI Approved :: MIT License
Classifier: Operating System :: POSIX
Classifier: Topic :: Utilities
